altscore_workflow_builder/Home.py
altscore_workflow_builder/__init__.py
altscore_workflow_builder/custom_tasks_utils.py
altscore_workflow_builder/flow_definition_utils.py
altscore_workflow_builder/input_override_utils.py
altscore_workflow_builder/launch_app.py
altscore_workflow_builder/native_tasks_utils.py
altscore_workflow_builder/task.py
altscore_workflow_builder/utils.py
altscore_workflow_builder/workflow.py
altscore_workflow_builder/pages/Borrowers.py
altscore_workflow_builder/pages/Evaluators.py
altscore_workflow_builder/pages/Packages.py
altscore_workflow_builder/pages/Rules.py
altscore_workflow_builder/pages/Workflow_Inspector.py
altscore_workflow_builder/pages/Workflow_builder.py
altscore_workflow_builder/pages/__init__.py
altscore_workflow_builder-0.0.24.dist-info/LICENSE
altscore_workflow_builder-0.0.24.dist-info/METADATA
altscore_workflow_builder-0.0.24.dist-info/WHEEL
altscore_workflow_builder-0.0.24.dist-info/entry_points.txt
altscore_workflow_builder-0.0.24.dist-info/top_level.txt
altscore_workflow_builder-0.0.24.dist-info/RECORD
