Metadata-Version: 2.1
Name: altscore-workflow-builder
Version: 0.0.24
Summary: Streamlit-based workflow builder for AltScore
Home-page: https://github.com/altscore/altscore-python
Author: AltScore
Author-email: developers@altscore.ai
License: MIT
Classifier: Intended Audience :: Developers
Classifier: License :: OSI Approved :: MIT License
Classifier: Operating System :: OS Independent
Requires-Python: >=3.8
License-File: LICENSE
Requires-Dist: python-dotenv
Requires-Dist: loguru
Requires-Dist: click
Requires-Dist: requests
Requires-Dist: pydantic ==1.10.13
Requires-Dist: httpx
Requires-Dist: stringcase
Requires-Dist: python-decouple
Requires-Dist: python-dateutil ==2.8.2
Requires-Dist: pyjwt
Requires-Dist: altscore
Requires-Dist: streamlit
Requires-Dist: streamlit-agraph
